napari_cochlea_synapse_seg/__init__.py
napari_cochlea_synapse_seg/_reader.py
napari_cochlea_synapse_seg/_sample_data.py
napari_cochlea_synapse_seg/_widget.py
napari_cochlea_synapse_seg/_writer.py
napari_cochlea_synapse_seg/napari.yaml
napari_cochlea_synapse_seg/_tests/__init__.py
napari_cochlea_synapse_seg/_tests/test_sample_data.py
cochlea_synapseg-0.0.1.dist-info/LICENSE
cochlea_synapseg-0.0.1.dist-info/METADATA
cochlea_synapseg-0.0.1.dist-info/WHEEL
cochlea_synapseg-0.0.1.dist-info/entry_points.txt
cochlea_synapseg-0.0.1.dist-info/top_level.txt
cochlea_synapseg-0.0.1.dist-info/RECORD
